dsagent/__init__.py
dsagent/cli.py
dsagent/agents/__init__.py
dsagent/agents/base.py
dsagent/agents/conversational.py
dsagent/cli/__init__.py
dsagent/cli/banner.py
dsagent/cli/commands.py
dsagent/cli/init.py
dsagent/cli/main.py
dsagent/cli/mcp_cmd.py
dsagent/cli/renderer.py
dsagent/cli/repl.py
dsagent/cli/run.py
dsagent/cli/skills_cmd.py
dsagent/core/__init__.py
dsagent/core/context.py
dsagent/core/engine.py
dsagent/core/executor.py
dsagent/core/hitl.py
dsagent/core/planner.py
dsagent/kernel/__init__.py
dsagent/kernel/backend.py
dsagent/kernel/introspector.py
dsagent/kernel/local.py
dsagent/memory/__init__.py
dsagent/memory/summarizer.py
dsagent/observability/__init__.py
dsagent/observability/config.py
dsagent/observability/manager.py
dsagent/prompts/__init__.py
dsagent/prompts/builder.py
dsagent/prompts/sections.py
dsagent/schema/__init__.py
dsagent/schema/models.py
dsagent/server/__init__.py
dsagent/server/app.py
dsagent/server/deps.py
dsagent/server/manager.py
dsagent/server/models.py
dsagent/server/websocket.py
dsagent/server/routes/__init__.py
dsagent/server/routes/artifacts.py
dsagent/server/routes/chat.py
dsagent/server/routes/files.py
dsagent/server/routes/health.py
dsagent/server/routes/hitl.py
dsagent/server/routes/kernel.py
dsagent/server/routes/sessions.py
dsagent/session/__init__.py
dsagent/session/logger.py
dsagent/session/manager.py
dsagent/session/models.py
dsagent/session/store.py
dsagent/skills/__init__.py
dsagent/skills/installer.py
dsagent/skills/loader.py
dsagent/skills/models.py
dsagent/skills/registry.py
dsagent/tools/__init__.py
dsagent/tools/config.py
dsagent/tools/mcp_manager.py
dsagent/utils/__init__.py
dsagent/utils/logger.py
dsagent/utils/notebook.py
dsagent/utils/run_logger.py
dsagent/utils/validation.py
datascience_agent-0.8.3.dist-info/METADATA
datascience_agent-0.8.3.dist-info/WHEEL
datascience_agent-0.8.3.dist-info/entry_points.txt
datascience_agent-0.8.3.dist-info/licenses/LICENSE
datascience_agent-0.8.3.dist-info/RECORD
