Metadata-Version: 2.4
Name: datascience-agent
Version: 0.8.3
Summary: AI Agent with dynamic planning and persistent Jupyter kernel execution for data analysis
Project-URL: Homepage, https://github.com/nmlemus/dsagent
Project-URL: Documentation, https://github.com/nmlemus/dsagent#readme
Project-URL: Repository, https://github.com/nmlemus/dsagent
Author: DSAgent Contributors
License-Expression: MIT
License-File: LICENSE
Keywords: agent,ai,autonomous-agent,data-analysis,datascience-agent,dsagent,jupyter,llm,machine-learning,planner
Classifier: Development Status :: 3 - Alpha
Classifier: Intended Audience :: Developers
Classifier: Intended Audience :: Science/Research
Classifier: License :: OSI Approved :: MIT License
Classifier: Programming Language :: Python :: 3
Classifier: Programming Language :: Python :: 3.10
Classifier: Programming Language :: Python :: 3.11
Classifier: Programming Language :: Python :: 3.12
Classifier: Topic :: Scientific/Engineering :: Artificial Intelligence
Classifier: Topic :: Scientific/Engineering :: Information Analysis
Requires-Python: >=3.10
Requires-Dist: boruta>=0.3
Requires-Dist: ipykernel>=6.0.0
Requires-Dist: jupyter-client>=8.0.0
Requires-Dist: lightgbm>=4.0.0
Requires-Dist: litellm>=1.81.0
Requires-Dist: matplotlib>=3.7.0
Requires-Dist: numpy>=1.24.0
Requires-Dist: openpyxl>=3.1.0
Requires-Dist: pandas>=2.0.0
Requires-Dist: plotly>=5.18.0
Requires-Dist: polars>=0.20.0
Requires-Dist: prompt-toolkit>=3.0.0
Requires-Dist: pyarrow>=14.0.0
Requires-Dist: pycaret>=3.0.0
Requires-Dist: pydantic-settings>=2.0.0
Requires-Dist: pydantic>=2.0.0
Requires-Dist: python-dotenv>=1.0.0
Requires-Dist: pyyaml>=6.0.0
Requires-Dist: rich>=13.0.0
Requires-Dist: scikit-learn>=1.5.0
Requires-Dist: scipy>=1.11.0
Requires-Dist: seaborn>=0.12.0
Requires-Dist: statsmodels>=0.14.0
Requires-Dist: tqdm>=4.66.0
Requires-Dist: watchdog>=3.0.0
Requires-Dist: xgboost>=2.0.0
Provides-Extra: api
Requires-Dist: fastapi>=0.100.0; extra == 'api'
Requires-Dist: httpx>=0.25.0; extra == 'api'
Requires-Dist: python-multipart>=0.0.6; extra == 'api'
Requires-Dist: sse-starlette>=1.0.0; extra == 'api'
Requires-Dist: uvicorn>=0.20.0; extra == 'api'
Requires-Dist: websockets>=12.0; extra == 'api'
Provides-Extra: dev
Requires-Dist: mypy>=1.0.0; extra == 'dev'
Requires-Dist: pytest-asyncio>=0.21.0; extra == 'dev'
Requires-Dist: pytest>=7.0.0; extra == 'dev'
Requires-Dist: ruff>=0.1.0; extra == 'dev'
Provides-Extra: docs
Requires-Dist: mkdocs-gen-files>=0.5.0; extra == 'docs'
Requires-Dist: mkdocs-literate-nav>=0.6.0; extra == 'docs'
Requires-Dist: mkdocs-material>=9.5.0; extra == 'docs'
Requires-Dist: mkdocs>=1.5.0; extra == 'docs'
Requires-Dist: mkdocstrings[python]>=0.24.0; extra == 'docs'
Provides-Extra: mcp
Requires-Dist: mcp>=1.0.0; extra == 'mcp'
